multimolecule/__init__.py
multimolecule/_version.py
multimolecule/defaults.py
multimolecule/data/README.md
multimolecule/data/README.zh.md
multimolecule/data/__init__.py
multimolecule/data/dataset.py
multimolecule/data/functional.py
multimolecule/data/registry.py
multimolecule/data/utils.py
multimolecule/datasets/README.md
multimolecule/datasets/README.zh.md
multimolecule/datasets/conversion_utils.py
multimolecule/datasets/archiveii/README.md
multimolecule/datasets/archiveii/archiveii.py
multimolecule/datasets/bprna_1m/README.md
multimolecule/datasets/bprna_1m/bprna_1m.py
multimolecule/datasets/bprna_new/README.md
multimolecule/datasets/bprna_new/bprna_new.py
multimolecule/datasets/bprna_spot/README.md
multimolecule/datasets/bprna_spot/bprna_spot.py
multimolecule/datasets/eternabench_cm/README.md
multimolecule/datasets/eternabench_cm/eternabench_cm.py
multimolecule/datasets/eternabench_external/README.md
multimolecule/datasets/eternabench_external/eternabench_external.py
multimolecule/datasets/eternabench_switch/README.md
multimolecule/datasets/eternabench_switch/eternabench_switch.py
multimolecule/datasets/gencode/README.md
multimolecule/datasets/gencode/gencode.py
multimolecule/datasets/rfam/README.md
multimolecule/datasets/rfam/rfam.py
multimolecule/datasets/rivas/README.md
multimolecule/datasets/rivas/rivas.py
multimolecule/datasets/rnacentral/README.md
multimolecule/datasets/rnacentral/modifications.py
multimolecule/datasets/rnacentral/rnacentral.py
multimolecule/datasets/rnacentral/secondary_structure.py
multimolecule/datasets/rnacentral/utils.py
multimolecule/datasets/rnastralign/README.md
multimolecule/datasets/rnastralign/rnastralign.py
multimolecule/datasets/ryos/README.md
multimolecule/datasets/ryos/ryos.py
multimolecule/models/README.md
multimolecule/models/README.zh.md
multimolecule/models/__init__.py
multimolecule/models/configuration_utils.py
multimolecule/models/conversion_utils.py
multimolecule/models/modeling_auto.py
multimolecule-0.0.8.dist-info/METADATA
multimolecule-0.0.8.dist-info/WHEEL
multimolecule-0.0.8.dist-info/top_level.txt
multimolecule-0.0.8.dist-info/RECORD
