Metadata-Version: 2.4
Name: multimolecule
Version: 0.0.8
Summary: Accelerate Molecular Biology Research with Machine Learning
Author-email: Zhiyuan Chen <this@zyc.ai>
Maintainer-email: Zhiyuan Chen <this@zyc.ai>
License: # GNU AFFERO GENERAL PUBLIC LICENSE
Project-URL: documentation, https://multimolecule.danling.org
Project-URL: homepage, https://multimolecule.danling.org
Project-URL: repository, https://github.com/DLS5-Omics/multimolecule
Keywords: deep-learning,DNA,machine-learning,Protein,RNA
Classifier: Development Status :: 2 - Pre-Alpha
Classifier: Intended Audience :: Developers
Classifier: Intended Audience :: Education
Classifier: Intended Audience :: Science/Research
Classifier: License :: OSI Approved :: GNU Affero General Public License v3 or later (AGPLv3+)
Classifier: Operating System :: OS Independent
Classifier: Programming Language :: Python :: 3 :: Only
Classifier: Programming Language :: Python :: 3.8
Classifier: Programming Language :: Python :: 3.9
Classifier: Programming Language :: Python :: 3.10
Classifier: Programming Language :: Python :: 3.11
Classifier: Programming Language :: Python :: 3.12
Classifier: Programming Language :: Python :: 3.13
Classifier: Topic :: Scientific/Engineering :: Artificial Intelligence
Requires-Python: >=3.8
Requires-Dist: accelerate
Requires-Dist: chanfig>=0.0.105
Requires-Dist: danling[torch]>=0.3.11
Requires-Dist: datasets
Requires-Dist: strenum; python_version < "3.11"
Requires-Dist: torch
Requires-Dist: transformers
